valda/__init__.py
valda/beta_shapley.py
valda/cs_shapley.py
valda/eval.py
valda/inf_func.py
valda/loo.py
valda/metrics.py
valda/params.py
valda/pyclassifier.py
valda/tmc_shapley.py
valda/util.py
valda/valuation.py
valda-0.1.10.dist-info/LICENSE.rst
valda-0.1.10.dist-info/METADATA
valda-0.1.10.dist-info/WHEEL
valda-0.1.10.dist-info/top_level.txt
valda-0.1.10.dist-info/RECORD
