Metadata-Version: 2.1
Name: valda
Version: 0.1.10
Summary: A Data Valuation Package for Machine Learning
Author-email: Yangfeng Ji <yangfeng@virginia.edu>, Stephanie Schoch <sns2gr@virginia.edu>
Project-URL: Homepage, https://uvanlp.org/valda
Project-URL: Bug Tracker, https://github.com/uvanlp/valda/issues
Keywords: data valuation
Classifier: Programming Language :: Python :: 3
Classifier: License :: OSI Approved :: MIT License
Classifier: Operating System :: OS Independent
Requires-Python: >=3.6
License-File: LICENSE.rst
Requires-Dist: scikit-learn
Requires-Dist: tqdm
